adxl355/__init__.py
adxl355/adxl355_definitions.py
adxl355/adxl355_spi.py
tests/__init__.py
tests/test_adxl355.py
adxl355_library-0.1.0.dist-info/METADATA
adxl355_library-0.1.0.dist-info/WHEEL
adxl355_library-0.1.0.dist-info/top_level.txt
adxl355_library-0.1.0.dist-info/RECORD
