Metadata-Version: 2.1
Name: adxl355-library
Version: 0.1.0
Summary: A Python library for interfacing with the ADXL355 accelerometer via SPI.
Home-page: https://github.com/oaslananka/adxl355_spi_library
Author: oaslananka
Author-email: info@oaslananka.dev
License: MIT
Project-URL: Documentation, https://github.com/oaslananka/adxl355_spi_library#readme
Project-URL: Source, https://github.com/oaslananka/adxl355_spi_library
Project-URL: Tracker, https://github.com/oaslananka/adxl355_spi_library/issues
Keywords: ADXL355 accelerometer SPI hardware
Classifier: Development Status :: 3 - Alpha
Classifier: Intended Audience :: Developers
Classifier: Topic :: Software Development :: Libraries :: Python Modules
Classifier: License :: OSI Approved :: MIT License
Classifier: Programming Language :: Python :: 3
Classifier: Programming Language :: Python :: 3.6
Classifier: Programming Language :: Python :: 3.7
Classifier: Programming Language :: Python :: 3.8
Classifier: Programming Language :: Python :: 3.9
Classifier: Programming Language :: Python :: 3.10
Classifier: Programming Language :: Python :: 3.11
Classifier: Operating System :: POSIX :: Linux
Requires-Python: >=3.6
Requires-Dist: spidev
Requires-Dist: wiringpi
